it_finance_api/VERSION
it_finance_api/__init__.py
it_finance_api/endpoints.py
it_finance_api/exceptions.py
it_finance_api/it_finance_api.py
it_finance_api/response.py
it_finance_api/version.py
it_finance_api/models/__init__.py
it_finance_api/models/account.py
it_finance_api/models/base.py
it_finance_api/models/credit_score.py
it_finance_api-0.0.5.dist-info/METADATA
it_finance_api-0.0.5.dist-info/WHEEL
it_finance_api-0.0.5.dist-info/top_level.txt
it_finance_api-0.0.5.dist-info/RECORD
