Metadata-Version: 2.1
Name: it-finance-api
Version: 0.0.5
Summary: A wrapper for it finance data
Home-page: https://github.com/telnet-data/it-finance-api
Author: Telnet Data
License: LGPLv3
Platform: UNKNOWN
Classifier: Programming Language :: Python
Classifier: License :: OSI Approved :: GNU General Public License v3 (GPLv3)
Requires-Python: >=3.6
Requires-Dist: requests
